{
	"authors": [
		"Quasinconsistent",
		"gdljjrod",
		"Jeffry Avila",
		"Samir2298",
		"libardomm",
		"Ultrameyda",
		"Belickade",
		"Takuhii",
		"Gaardus",
		"capSilver",
		"MoonshineIndustries",
		"ElDuniels",
		"Swervito",
		"Rockstock7",
		"GAD__Alexander",
		"setasorcer"
	],
	"content": [
		{
			"id": "ALADDIN",
			"title": "Aladdin - Nasira's Revenge",
			"version": "1.00",
			"author": "Quasinconsistent"
		},
		{
			"id": "ALUNDRA",
			"title": "Alundra",
			"version": "1.00",
			"author": "Quasinconsistent"
		},
		{
			"id": "BREATHIII",
			"title": "Breath of Fire III",
			"version": "1.00",
			"author": "Quasinconsistent"
		},
		{
			"id": "BREATHIV",
			"title": "Breath of Fire IV",
			"version": "1.00",
			"author": "Quasinconsistent"
		},
		{
			"id": "CHTRIGGER",
			"title": "Chrono Trigger",
			"version": "1.00",
			"author": "Quasinconsistent"
		},
		{
			"id": "CLADUNX2",
			"title": "ClaDun x2",
			"version": "1.00",
			"author": "Quasinconsistent"
		},
		{
			"id": "DARKSTALKERS",
			"title": "Darkstalkers Chronicle",
			"version": "1.00",
			"author": "Quasinconsistent"
		},
		{
			"id": "DIGIMONCARD",
			"title": "Digimon Digital Card Battle",
			"version": "1.00",
			"author": "Quasinconsistent"
		},
		{
			"id": "DIGIMONRUMBLE",
			"title": "Digimon Rumble Arena",
			"version": "1.00",
			"author": "Quasinconsistent"
		},
		{
			"id": "DIGIMONW",
			"title": "Digimon World",
			"version": "1.00",
			"author": "Quasinconsistent"
		},
		{
			"id": "DIGIMONW2",
			"title": "Digimon World 2",
			"version": "1.00",
			"author": "Quasinconsistent"
		},
		{
			"id": "DISGAEA",
			"title": "Disgaea",
			"version": "1.00",
			"author": "Quasinconsistent"
		},
		{
			"id": "DISGAEA2",
			"title": "Disgaea 2",
			"version": "1.00",
			"author": "Quasinconsistent"
		},
		{
			"id": "DISSIDIA",
			"title": "Dissidia Final Fantasy",
			"version": "1.00",
			"author": "Quasinconsistent"
		},
		{
			"id": "DISSIDIA012",
			"title": "Dissidia Final Fantasy - Duodecim 012",
			"version": "1.00",
			"author": "Quasinconsistent"
		},
		{
			"id": "FFI",
			"title": "Final Fantasy I",
			"version": "1.00",
			"author": "Quasinconsistent"
		},
		{
			"id": "FFII",
			"title": "Final Fantasy II",
			"version": "1.00",
			"author": "Quasinconsistent"
		},
		{
			"id": "FFIII",
			"title": "Final Fantasy III",
			"version": "1.00",
			"author": "Quasinconsistent"
		},
		{
			"id": "FFIV",
			"title": "Final Fantasy IV",
			"version": "1.00",
			"author": "Quasinconsistent"
		},
		{
			"id": "FFVI",
			"title": "Final Fantasy VI",
			"version": "1.00",
			"author": "Quasinconsistent"
		},
		{
			"id": "FFVII",
			"title": "Final Fantasy VII",
			"version": "1.00",
			"author": "Quasinconsistent"
		},
		{
			"id": "FFVIII",
			"title": "Final Fantasy VIII",
			"version": "1.00",
			"author": "Quasinconsistent"
		},
		{
			"id": "FFIX",
			"title": "Final Fantasy IX",
			"version": "1.00",
			"author": "Quasinconsistent"
		},
		{
			"id": "FFTACTICS",
			"title": "Final Fantasy Tactics - War of The Lions",
			"version": "1.00",
			"author": "Quasinconsistent"
		},
		{
			"id": "JEANNEARC",
			"title": "Jeanne d'Arc",
			"version": "1.00",
			"author": "Quasinconsistent"
		},
		{
			"id": "KLONOADOOR",
			"title": "Klonoa: Door to Phantomile",
			"version": "1.00",
			"author": "Quasinconsistent"
		},
		{
			"id": "KNIGHTNIGHT",
			"title": "Knights in the Nightmare",
			"version": "1.00",
			"author": "Quasinconsistent"
		},
		{
			"id": "LAPUCELLE",
			"title": "La Pucelle",
			"version": "1.00",
			"author": "Quasinconsistent"
		},
		{
			"id": "LEGACYKAIN",
			"title": "Legacy of Kain - Soul Reaver",
			"version": "1.00",
			"author": "Quasinconsistent"
		},
		{
			"id": "LEGDRAGOON",
			"title": "Legend of Dragoon",
			"version": "1.00",
			"author": "Quasinconsistent"
		},
		{
			"id": "LEGENDMANA",
			"title": "Legend of Mana",
			"version": "1.00",
			"author": "Quasinconsistent"
		},
		{
			"id": "MAKAIKINGDOM",
			"title": "Makai Kingdom",
			"version": "1.00",
			"author": "Quasinconsistent"
		},
		{
			"id": "MARVELCAPCOM",
			"title": "Marvel vs. Capcom",
			"version": "1.00",
			"author": "Quasinconsistent"
		},
		{
			"id": "MEDIEVIL",
			"title": "Medievil",
			"version": "1.00",
			"author": "Quasinconsistent"
		},
		{
			"id": "METALSLUGANTH",
			"title": "Metal SLug Anthology",
			"version": "1.00",
			"author": "Quasinconsistent"
		},
		{
			"id": "MH3ERDP",
			"title": "Monster Hunter 3rd Portable",
			"version": "1.00",
			"author": "Quasinconsistent"
		},
		{
			"id": "MHFUNITE",
			"title": "Monster Hunter Freedom Unite",
			"version": "1.00",
			"author": "Quasinconsistent"
		},
		{
			"id": "MK4",
			"title": "Mortal Kombat 4",
			"version": "1.00",
			"author": "Quasinconsistent"
		},
		{
			"id": "MKTRILOGY",
			"title": "Mortal Kombat Trilogy",
			"version": "1.00",
			"author": "Quasinconsistent"
		},
		{
			"id": "MKUNCHAINED",
			"title": "Mortal Kombat Unchained",
			"version": "1.00",
			"author": "Quasinconsistent"
		},
		{
			"id": "NARUTOSHIPPUDEN",
			"title": "Naruto Shippuden Ultimate Ninja Impact",
			"version": "1.00",
			"author": "Quasinconsistent"
		},
		{
			"id": "PSP2",
			"title": "Phantasy Star Portable 2",
			"version": "1.00",
			"author": "Quasinconsistent"
		},
		{
			"id": "PHANTOMBRAVE",
			"title": "Phantom Brave - The Hermuda Triangle",
			"version": "1.00",
			"author": "Quasinconsistent"
		},
		{
			"id": "POWERSTONECOL",
			"title": "Power Stone Collection",
			"version": "1.00",
			"author": "Quasinconsistent"
		},
		{
			"id": "PRINNY",
			"title": "Prinny",
			"version": "1.00",
			"author": "Quasinconsistent"
		},
		{
			"id": "PRINNY2",
			"title": "Prinny 2",
			"version": "1.00",
			"author": "Quasinconsistent"
		},
		{
			"id": "RAGNAROKT",
			"title": "Ragnarok Tactics",
			"version": "1.00",
			"author": "Quasinconsistent"
		},
		{
			"id": "TACTICSOGRE",
			"title": "Tactics Ogre",
			"version": "1.00",
			"author": "Quasinconsistent"
		},
		{
			"id": "VAGRANT",
			"title": "Vagrant Story",
			"version": "1.00",
			"author": "Quasinconsistent"
		},
		{
			"id": "XENOGEARS",
			"title": "Xenogears",
			"version": "1.00",
			"author": "Quasinconsistent"
		},
		{
			"id": "YGGDRA",
			"title": "Yggdra Union",
			"version": "1.00",
			"author": "Quasinconsistent"
		},
		{
			"id": "YSSEVEN",
			"title": "YS Seven",
			"version": "1.00",
			"author": "Quasinconsistent"
		},
		{
			"id": "CASTLESOTN",
			"title": "Castlevania: Symphony of the Night",
			"version": "1.00",
			"author": "gdljjrod"
		},
		{
			"id": "FFCCORE",
			"title": "Crisis Core: Final Fantasy VII",
			"version": "1.00",
			"author": "gdljjrod"
		},
		{
			"id": "FFTYPE0",
			"title": "Final Fantasy Type-0",
			"version": "1.00",
			"author": "gdljjrod"
		},
		{
			"id": "FFVII_2",
			"title": "Final Fantasy VII",
			"version": "1.00",
			"author": "gdljjrod"
		},
		{
			"id": "KHBBSFMIX",
			"title": "Kingdom Hearts Birth by Sleep Final Mix",
			"version": "1.00",
			"author": "gdljjrod"
		},
		{
			"id": "P3P",
			"title": "Persona Portable 3",
			"version": "1.00",
			"author": "gdljjrod"
		},
		{
			"id": "P3P_2",
			"title": "Persona Portable 3",
			"version": "1.00",
			"author": "gdljjrod"
		},
		{
			"id": "SH1",
			"title": "Silent Hill 1",
			"version": "1.00",
			"author": "gdljjrod"
		},
		{
			"id": "DINOCRISIS1",
			"title": "Dino Crisis 1",
			"version": "1.00",
			"author": "gdljjrod"
		},
		{
			"id": "ALONEDARK",
			"title": "Alone in the Dark",
			"version": "1.00",
			"author": "Jeffry Avila"
		},
		{
			"id": "CRASHB",
			"title": "Crash Bandicoot",
			"version": "1.00",
			"author": "Jeffry Avila"
		},
		{
			"id": "CRASHB2",
			"title": "Crash Bandicoot 2",
			"version": "1.00",
			"author": "Jeffry Avila"
		},
		{
			"id": "CRASHB3",
			"title": "Crash Bandicoot 3",
			"version": "1.00",
			"author": "Jeffry Avila"
		},
		{
			"id": "CRASHTEAMR",
			"title": "Crash Team Rancing",
			"version": "1.00",
			"author": "Jeffry Avila"
		},
		{
			"id": "CREATURES",
			"title": "Creatures",
			"version": "1.00",
			"author": "Jeffry Avila"
		},
		{
			"id": "CREATURES2",
			"title": "Creatures II",
			"version": "1.00",
			"author": "Jeffry Avila"
		},
		{
			"id": "FEAREFFECT",
			"title": "Fear Effect",
			"version": "1.00",
			"author": "Jeffry Avila"
		},
		{
			"id": "FEAREFFECT2",
			"title": "Fear Effect 2",
			"version": "1.00",
			"author": "Jeffry Avila"
		},
		{
			"id": "GALERIANS",
			"title": "Galerians",
			"version": "1.00",
			"author": "Jeffry Avila"
		},
		{
			"id": "MARTIANGUNIF",
			"title": "Martian Gothic Unification",
			"version": "1.00",
			"author": "Jeffry Avila"
		},
		{
			"id": "RE2",
			"title": "Resident Evil 2",
			"version": "1.00",
			"author": "Jeffry Avila"
		},
		{
			"id": "PEVEI",
			"title": "Parasit Eve I",
			"version": "1.00",
			"author": "Jeffry Avila"
		},
		{
			"id": "SOULREAVER",
			"title": "Legacy of Kain - Soul Reaver",
			"version": "1.00",
			"author": "Jeffry Avila"
		},
		{
			"id": "STARWARSREBELII",
			"title": "Star Wars Rebel Assault II",
			"version": "1.00",
			"author": "Jeffry Avila"
		},
		{
			"id": "VICECITY",
			"title": "GTA Vice City Stories",
			"version": "1.00",
			"author": "Samir2298"
		},
		{
			"id": "PEACEWALKER",
			"title": "Metal Gear Peace Walker",
			"version": "1.00",
			"author": "libardomm"
		},
		{
			"id": "PORTABLEOPS",
			"title": "Metal Gear Solid Portable OPS",
			"version": "1.00",
			"author": "libardomm"
		},
		{
			"id": "MGSTACTICAL",
			"title": "Metal Gear Solid Tactical Espionage",
			"version": "1.00",
			"author": "libardomm"
		},
		{
			"id": "GBA",
			"title": "Emulator GameBoy Advance",
			"version": "1.00",
			"author": "libardomm"
		},
		{
			"id": "FFTACTICS2",
			"title": "Final Fantasy Tactics - War of The Lions",
			"version": "1.00",
			"author": "libardomm"
		},
		{
			"id": "CHRONOTRIGGER",
			"title": "Chrono Trigger",
			"version": "1.00",
			"author": "libardomm"
		},
		{
			"id": "PERSONA3",
			"title": "Persona Portable 3",
			"version": "1.00",
			"author": "libardomm"
		},
		{
			"id": "LITTLERALPH",
			"title": "Adventures of Little Ralph",
			"version": "1.00",
			"author": "Ultrameyda"
		},
		{
			"id": "LOMAX",
			"title": "Adventures of Lomax",
			"version": "1.00",
			"author": "Ultrameyda"
		},
		{
			"id": "BLASTO",
			"title": "Blasto",
			"version": "1.00",
			"author": "Ultrameyda"
		},
		{
			"id": "BLOODLEGACYKAIN",
			"title": "Blood Omen - Legacy of Kain",
			"version": "1.00",
			"author": "Ultrameyda"
		},
		{
			"id": "BLOODYROAR2",
			"title": "Bloody Roar 2",
			"version": "1.00",
			"author": "Ultrameyda"
		},
		{
			"id": "BRAVEFENCER",
			"title": "Brave Fencer Musashi",
			"version": "1.00",
			"author": "Ultrameyda"
		},
		{
			"id": "BREATHFIREIII2",
			"title": "Breath of Fire III",
			"version": "1.00",
			"author": "Ultrameyda"
		},
		{
			"id": "BREATHFIREIV2",
			"title": "Breath of Fire IV",
			"version": "1.00",
			"author": "Ultrameyda"
		},
		{
			"id": "BUSHIDO",
			"title": "Bushido Blade",
			"version": "1.00",
			"author": "Ultrameyda"
		},
		{
			"id": "BUSTMOVE4",
			"title": "Bust A Move 4",
			"version": "1.00",
			"author": "Ultrameyda"
		},
		{
			"id": "CASTLECHRONICLES",
			"title": "Castlevania Chronicles",
			"version": "1.00",
			"author": "Ultrameyda"
		},
		{
			"id": "CASTLESOTN2",
			"title": "Castlevania: Symphony of the Night",
			"version": "1.00",
			"author": "Ultrameyda"
		},
		{
			"id": "CHOANIKI",
			"title": "Cho Aniki",
			"version": "1.00",
			"author": "Ultrameyda"
		},
		{
			"id": "CHRONOCROSS",
			"title": "Chrono Cross",
			"version": "1.00",
			"author": "Ultrameyda"
		},
		{
			"id": "COLONYWARS",
			"title": "Colony Wars",
			"version": "1.00",
			"author": "Ultrameyda"
		},
		{
			"id": "CRASHBANDICOOT",
			"title": "Crash Bandicoot",
			"version": "1.00",
			"author": "Ultrameyda"
		},
		{
			"id": "DESTREGA",
			"title": "Destrega",
			"version": "1.00",
			"author": "Ultrameyda"
		},
		{
			"id": "DINOCRISISS",
			"title": "Dino Crisis",
			"version": "1.00",
			"author": "Ultrameyda"
		},
		{
			"id": "ECHONIGHT2",
			"title": "Echo Night 2",
			"version": "1.00",
			"author": "Ultrameyda"
		},
		{
			"id": "EINHANDER",
			"title": "Einhander",
			"version": "1.00",
			"author": "Ultrameyda"
		},
		{
			"id": "FADETOBLACK",
			"title": "Fade to Black",
			"version": "1.00",
			"author": "Ultrameyda"
		},
		{
			"id": "FANTNIGHTSDREAM",
			"title": "Fantasic Nights Dreams Cotton",
			"version": "1.00",
			"author": "Ultrameyda"
		},
		{
			"id": "FINALFANTASYIX",
			"title": "Final Fantasy IX",
			"version": "1.00",
			"author": "Ultrameyda"
		},
		{
			"id": "FINALFANTASYVII",
			"title": "Final Fantasy VII",
			"version": "1.00",
			"author": "Ultrameyda"
		},
		{
			"id": "FINALFANTASYVIII",
			"title": "Final Fantasy VIII",
			"version": "1.00",
			"author": "Ultrameyda"
		},
		{
			"id": "FISTNORTHSTAR",
			"title": "Fist of the North Star",
			"version": "1.00",
			"author": "Ultrameyda"
		},
		{
			"id": "FRONTMISSION3",
			"title": "Front Mission 3",
			"version": "1.00",
			"author": "Ultrameyda"
		},
		{
			"id": "GDARIUS",
			"title": "G-Darius",
			"version": "1.00",
			"author": "Ultrameyda"
		},
		{
			"id": "GRANDIA",
			"title": "Grandia",
			"version": "1.00",
			"author": "Ultrameyda"
		},
		{
			"id": "GRANTSTREAM",
			"title": "Granstream Saga",
			"version": "1.00",
			"author": "Ultrameyda"
		},
		{
			"id": "HARMFULPARK",
			"title": "Harmful Park",
			"version": "1.00",
			"author": "Ultrameyda"
		},
		{
			"id": "HEARTDARKNESS",
			"title": "Heart of Darkness",
			"version": "1.00",
			"author": "Ultrameyda"
		},
		{
			"id": "HELLNIGHT",
			"title": "Hell Night",
			"version": "1.00",
			"author": "Ultrameyda"
		},
		{
			"id": "INCRECRISIS",
			"title": "Incredible Crisis",
			"version": "1.00",
			"author": "Ultrameyda"
		},
		{
			"id": "ISSECTION",
			"title": "IS - Internal Section",
			"version": "1.00",
			"author": "Ultrameyda"
		},
		{
			"id": "FF5PS1RETRO",
			"title": "Final Fantasy V PS1 Retro",
			"version": "1.00",
			"author": "Belickade"
		},
		{
			"id": "FF6PS1RETRO",
			"title": "Final Fantasy VI PS1 Retro",
			"version": "1.00",
			"author": "Belickade"
		},
		{
			"id": "FF7PS1RETRO",
			"title": "Final Fantasy VII PS1 Retro",
			"version": "1.00",
			"author": "Belickade"
		},
		{
			"id": "FF8PS1RETRO",
			"title": "Final Fantasy VIII PS1 Retro",
			"version": "1.00",
			"author": "Belickade"
		},
		{
			"id": "FF9PS1RETRO",
			"title": "Final Fantasy IX PS1 Retro",
			"version": "1.00",
			"author": "Belickade"
		},
		{
			"id": "FFORIGINSPS1RETRO",
			"title": "Final Fantasy Origins PS1 Retro",
			"version": "1.00",
			"author": "Belickade"
		},
		{
			"id": "FFTACTICSPS1RETRO",
			"title": "Final Fantasy Tactics PS1 Retro",
			"version": "1.00",
			"author": "Belickade"
		},
		{
			"id": "2XEXTREMEPS1RETRO",
			"title": "2X Extreme PS1 Retro",
			"version": "1.00",
			"manual": "true",
			"author": "Belickade"
		},
		{
			"id": "BLOODKAINPS1RETRO",
			"title": "Blood Omen Legacy of Kain PS1 Retro",
			"version": "1.00",
			"manual": "true",
			"author": "Belickade"
		},
		{
			"id": "ALUNDRAPS1RETRO",
			"title": "Alundra PS1 Retro",
			"version": "1.00",
			"author": "Belickade"
		},
		{
			"id": "BILLIARDSPS1RETRO",
			"title": "Backstreet Billiards PS1 Retro",
			"version": "1.00",
			"manual": "true",
			"author": "Belickade"
		},
		{
			"id": "BOMBRACEPS1RETRO",
			"title": "Bomberman Fantasy Race PS1 Retro",
			"version": "1.00",
			"manual": "true",
			"author": "Belickade"
		},
		{
			"id": "BOMBPARTYPS1RETRO",
			"title": "Bomberman Party Edition PS1 Retro",
			"version": "1.00",
			"manual": "true",
			"author": "Belickade"
		},
		{
			"id": "ARCLADPS1RETRO",
			"title": "Arc the Lad PS1 Retro",
			"version": "1.00",
			"manual": "true",
			"author": "Belickade"
		},
		{
			"id": "ARCLAD2PS1RETRO",
			"title": "Arc the Lad 2 PS1 Retro",
			"version": "1.00",
			"author": "Belickade"
		},
		{
			"id": "ARCLAD3PS1RETRO",
			"title": "Arc the Lad 3 PS1 Retro",
			"version": "1.00",
			"author": "Belickade"
		},
		{
			"id": "ARCTOURPS1RETRO",
			"title": "Arc Arena Monster Tournament PS1 Retro",
			"version": "1.00",
			"manual": "true",
			"author": "Belickade"
		},
		{
			"id": "BOXINGPS1RETRO",
			"title": "Boxing PS1 Retro",
			"version": "1.00",
			"manual": "true",
			"author": "Belickade"
		},
		{
			"id": "BREATHFIRE4PS1RETRO",
			"title": "Breath of Fire IV PS1 Retro",
			"version": "1.00",
			"manual": "true",
			"author": "Belickade"
		},
		{
			"id": "BHUNTERPS1RETRO",
			"title": "Battle Hunter PS1 Retro",
			"version": "1.00",
			"manual": "true",
			"author": "Belickade"
		},
		{
			"id": "ALLDBALLPS1RETRO",
			"title": "AllStar Slammin DBall PS1 Retro",
			"version": "1.00",
			"manual": "true",
			"author": "Belickade"
		},
		{
			"id": "ACESAIRPS1RETRO",
			"title": "Aces of the Air PS1 Retro",
			"version": "1.00",
			"manual": "true",
			"author": "Belickade"
		},
		{
			"id": "ARMCOREPS1RETRO",
			"title": "Armored Core PS1 Retro",
			"version": "1.00",
			"manual": "true",
			"author": "Belickade"
		},
		{
			"id": "BLOODROAR2PS1RETRO",
			"title": "Bloody Roar 2 PS1 Retro",
			"version": "1.00",
			"manual": "true",
			"author": "Belickade"
		},
		{
			"id": "CASTLESOTNPS1RETRO",
			"title": "Castlevania - SotN PS1 Retro",
			"version": "1.00",
			"manual": "true",
			"author": "Belickade"
		},
		{
			"id": "CASTLECHROPS1RETRO",
			"title": "Castlevania Chronicles PS1 Retro",
			"version": "1.00",
			"manual": "true",
			"author": "Belickade"
		},
		{
			"id": "CHRONOCROSSPS1RETRO",
			"title": "Chrono Cross PS1 Retro",
			"version": "1.00",
			"manual": "true",
			"author": "Belickade"
		},
		{
			"id": "CHRONOTRIPS1RETRO",
			"title": "Chrono Trigger PS1 Retro",
			"version": "1.00",
			"manual": "true",
			"author": "Belickade"
		},
		{
			"id": "CRASHBANDWARPS1RETRO",
			"title": "Crash Bandicoot Warped PS1 Retro",
			"version": "1.00",
			"manual": "true",
			"author": "Belickade"
		},
		{
			"id": "CRASHBAND1PS1RETRO",
			"title": "Crash Bandicoot 1 PS1 Retro",
			"version": "1.00",
			"manual": "true",
			"author": "Belickade"
		},
		{
			"id": "CRASHBAND2PS1RETRO",
			"title": "Crash Bandicoot 2 Cortex PS1 Retro",
			"version": "1.00",
			"manual": "true",
			"author": "Belickade"
		},
		{
			"id": "CRASHBANDTRPS1RETRO",
			"title": "Crash Team Racing PS1 Retro",
			"version": "1.00",
			"manual": "true",
			"author": "Belickade"
		},
		{
			"id": "DINOCRISIS1PS1RETRO",
			"title": "Dino Crisis 1 PS1 Retro",
			"version": "1.00",
			"manual": "true",
			"author": "Belickade"
		},
		{
			"id": "DINOCRISIS2PS1RETRO",
			"title": "Dino Crisis 2 PS1 Retro",
			"version": "1.00",
			"manual": "true",
			"author": "Belickade"
		},
		{
			"id": "GRANDIAPS1RETRO",
			"title": "Grandia PS1 Retro",
			"version": "1.00",
			"author": "Belickade"
		},
		{
			"id": "HARVESTNATUREPS1RETRO",
			"title": "Harvest Moon Back to Nature PS1 Retro",
			"version": "1.00",
			"manual": "true",
			"author": "Belickade"
		},
		{
			"id": "KLONOAPS1RETRO",
			"title": "Klonoa Door to Phantomile PS1 Retro",
			"version": "1.00",
			"manual": "true",
			"author": "Belickade"
		},
		{
			"id": "LEGACYKAINPS1RETRO",
			"title": "Legacy of Kain Soul Reaver PS1 Retro",
			"version": "1.00",
			"manual": "true",
			"author": "Belickade"
		},
		{
			"id": "LEGDRAGOONPS1RETRO",
			"title": "Legend of Dragoon PS1 Retro",
			"version": "1.00",
			"manual": "true",
			"author": "Belickade"
		},
		{
			"id": "LEGMANAPS1RETRO",
			"title": "Legend of Mana PS1 Retro",
			"version": "1.00",
			"manual": "true",
			"author": "Belickade"
		},
		{
			"id": "MLEGENDS1PS1RETRO",
			"title": "Mega Man Legends 1 PS1 Retro",
			"version": "1.00",
			"manual": "true",
			"author": "Belickade"
		},
		{
			"id": "MLEGENDS2PS1RETRO",
			"title": "Mega Man Legends 2 PS1 Retro",
			"version": "1.00",
			"manual": "true",
			"author": "Belickade"
		},
		{
			"id": "MEGAMANX4PS1RETRO",
			"title": "Mega Man X4 PS1 Retro",
			"version": "1.00",
			"manual": "true",
			"author": "Belickade"
		},
		{
			"id": "MEGAMANX5PS1RETRO",
			"title": "Mega Man X5 PS1 Retro",
			"version": "1.00",
			"manual": "true",
			"author": "Belickade"
		},
		{
			"id": "RE3NEMESISPS1RETRO",
			"title": "Resident Evil 3 Nemesis PS1 Retro",
			"version": "1.00",
			"manual": "true",
			"author": "Belickade"
		},
		{
			"id": "RE2DUALSHOCKPS1RETRO",
			"title": "RE Evil 2 Dual Shock Version PS1 Retro",
			"version": "1.00",
			"manual": "true",
			"author": "Belickade"
		},
		{
			"id": "REDIRECTORCUTPS1RETRO",
			"title": "Resident Evil Directors Cut PS1 Retro",
			"version": "1.00",
			"manual": "true",
			"author": "Belickade"
		},
		{
			"id": "SHILLPS1RETRO",
			"title": "Silent Hill 1 PS1 Retro",
			"version": "1.00",
			"manual": "true",
			"author": "Belickade"
		},
		{
			"id": "METALGSOLIDPS1RETRO",
			"title": "Metal Gear Solid PS1 Retro",
			"version": "1.00",
			"author": "Belickade"
		},
		{
			"id": "METALGVRPS1RETRO",
			"title": "Metal Gear Solid VR Missions PS1 Retro",
			"version": "1.00",
			"manual": "true",
			"author": "Belickade"
		},
		{
			"id": "MSLUGXPS1RETRO",
			"title": "Metal Slug X PS1 Retro",
			"version": "1.00",
			"manual": "true",
			"author": "Belickade"
		},
		{
			"id": "PEVE1PS1RETRO",
			"title": "Parasite Eve 1 PS1 Retro",
			"version": "1.00",
			"manual": "true",
			"author": "Belickade"
		},
		{
			"id": "PEVE2PS1RETRO",
			"title": "Parasite Eve 2 PS1 Retro",
			"version": "1.00",
			"manual": "true",
			"author": "Belickade"
		},
		{
			"id": "P2ETERNALPS1RETRO",
			"title": "Persona 2 Eternal Punishment PS1 Retro",
			"version": "1.00",
			"author": "Belickade"
		},
		{
			"id": "RAYMANPS1RETRO",
			"title": "Rayman PS1 Retro",
			"version": "1.00",
			"manual": "true",
			"author": "Belickade"
		},
		{
			"id": "RAYMAN2PS1RETRO",
			"title": "Rayman 2 The Great Escape PS1 Retro",
			"version": "1.00",
			"manual": "true",
			"author": "Belickade"
		},
		{
			"id": "SPYRO1PS1RETRO",
			"title": "Spyro the Dragon 1 PS1 Retro",
			"version": "1.00",
			"manual": "true",
			"author": "Belickade"
		},
		{
			"id": "SPYRO2PS1RETRO",
			"title": "Spyro the Dragon 2 PS1 Retro",
			"version": "1.00",
			"manual": "true",
			"author": "Belickade"
		},
		{
			"id": "SPYRO3PS1RETRO",
			"title": "Spyro the Dragon 3 PS1 Retro",
			"version": "1.00",
			"manual": "true",
			"author": "Belickade"
		},
		{
			"id": "SUIKODEN1PS1RETRO",
			"title": "Suikoden 1 PS1 Retro",
			"version": "1.00",
			"manual": "true",
			"author": "Belickade"
		},
		{
			"id": "SUIKODEN2PS1RETRO",
			"title": "Suikoden 2 PS1 Retro",
			"version": "1.00",
			"manual": "true",
			"author": "Belickade"
		},
		{
			"id": "VAGRANTPS1RETRO",
			"title": "Vagrant Story PS1 Retro",
			"version": "1.00",
			"manual": "true",
			"author": "Belickade"
		},
		{
			"id": "WILDARMS1PS1RETRO",
			"title": "WildArms 1 PS1 Retro",
			"version": "1.00",
			"author": "Belickade"
		},
		{
			"id": "WILDARMS2PS1RETRO",
			"title": "WildArms 2 PS1 Retro",
			"version": "1.00",
			"author": "Belickade"
		},
		{
			"id": "XENOGEARSPS1RETRO",
			"title": "Xenogears PS1 Retro",
			"version": "1.00",
			"manual": "true",
			"author": "Belickade"
		},
		{
			"id": "BLOODYPS1RETRO",
			"title": "Bloody Roar 1 PS1 Retro",
			"version": "1.00",
			"manual": "true",
			"author": "Belickade"
		},
		{
			"id": "BUSTMOVE4PS1RETRO",
			"title": "Bust A Move 4 PS1 Retro",
			"version": "1.00",
			"manual": "true",
			"author": "Belickade"
		},
		{
			"id": "BOWLINGPS1RETRO",
			"title": "Bowling PS1 Retro",
			"version": "1.00",
			"manual": "true",
			"author": "Belickade"
		},
		{
			"id": "YSARK",
			"title": "Ys VI: The Ark Of Napishtim Retro",
			"version": "1.00",
			"manual": "true",
			"author": "Belickade"
		},
		{
			"id": "YSSEVENRETRO",
			"title": "Ys SEVEN Retro",
			"version": "1.00",
			"manual": "true",
			"author": "Belickade"
		},
		{
			"id": "YSOTAH",
			"title": "Ys - The Oath in Felghana Retro",
			"version": "1.00",
			"manual": "true",
			"author": "Belickade"
		},
		{
			"id": "YSI_IICHRONICLES",
			"title": "Ys I & II Chronicles Retro",
			"version": "1.00",
			"manual": "true",
			"author": "Belickade"
		},
		{
			"id": "MM8RETRO",
			"title": "Megaman 8 Retro",
			"version": "1.00",
			"manual": "true",
			"author": "Belickade"
		},
		{
			"id": "MEGAMANHUNTERXRETRO",
			"title": "Mega Man - Maverick Hunter X Retro",
			"version": "1.00",
			"manual": "true",
			"author": "Belickade"
		},
		{
			"id": "HOKUTONOKENRAOGAIDENTENNOHAO",
			"title": "Hokuto no Ken - Rao Gaiden - Ten no Hao",
			"version": "1.00",
			"author": "Takuhii"
		},
		{
			"id": "ASSASSINSCREEDBLOODLINES",
			"title": "Assassins Creed Bloodlines",
			"version": "1.00",
			"author": "Takuhii"
		},
		{
			"id": "WIPEOUTPULSE",
			"title": "WipEout Pulse",
			"version": "1.00",
			"author": "Takuhii"
		},
		{
			"id": "WIPEOUTPURE",
			"title": "WipEout Pure",
			"version": "1.00",
			"author": "Takuhii"
		},
		{
			"id": "WIPEOUT",
			"title": "Wipeout",
			"version": "1.00",
			"author": "Takuhii"
		},
		{
			"id": "LOCOROCO2",
			"title": "LocoRoco 2",
			"version": "1.00",
			"author": "Takuhii"
		},
		{
			"id": "LOCOROCOMIDNIGHTCARNIVAL",
			"title": "LocoRoco Midnight Carnival",
			"version": "1.00",
			"author": "Takuhii"
		},
		{
			"id": "CRAZYTAXIFAREWARS",
			"title": "Crazy Taxi - Fare Wars",
			"version": "1.00",
			"author": "Takuhii"
		},
		{
			"id": "LOCOROCO",
			"title": "LocoRoco",
			"version": "1.00",
			"author": "Takuhii"
		},
		{
			"id": "OUTRUN2006COASTTOCOAST",
			"title": "Outrun 2006 - Coast to Coast",
			"version": "1.00",
			"author": "Takuhii"
		},
		{
			"id": "GODOFWAR_CHAINSOFOLYMPUS",
			"title": "God of War - Chains of Olympus",
			"version": "1.00",
			"author": "Takuhii"
		},
		{
			"id": "GODOFWAR_GHOSTOFSPARTA",
			"title": "God of War - Ghost of Sparta",
			"version": "1.00",
			"author": "Takuhii"
		},
		{
			"id": "DRIVER76",
			"title": "Driver 76",
			"version": "1.00",
			"author": "Takuhii"
		},
		{
			"id": "7THDRAGON2020",
			"title": "7th Dragon 2020",
			"version": "1.01",
			"author": "Gaardus"
		},
		{
			"id": "BREATHFIREIII3",
			"title": "Breath of Fire III",
			"version": "1.01",
			"author": "Gaardus"
		},
		{
			"id": "BLACKROCK",
			"title": "Black Rock Shooter - The Game",
			"version": "1.01",
			"author": "Gaardus"
		},
		{
			"id": "BLADEDANCER",
			"title": "Blade Dancer: Lineage of Light",
			"version": "1.01",
			"author": "Gaardus"
		},
		{
			"id": "BLAZINGSOULS",
			"title": "Blazing Souls Accelate",
			"version": "1.00",
			"manual": "true",
			"author": "Gaardus"
		},
		{
			"id": "CASTLEVANIAX",
			"title": "Castlevania - The Dracula X Chronicles",
			"version": "1.01",
			"author": "Gaardus"
		},
		{
			"id": "CLADUN",
			"title": "ClaDun - This is an RPG",
			"version": "1.01",
			"manual": "true",
			"author": "Gaardus"
		},
		{
			"id": "CLASSOFHEROES",
			"title": "Class of Heroes",
			"version": "1.01",
			"author": "Gaardus"
		},
		{
			"id": "CRIMSONGEMSAGA",
			"title": "Crimson Gem Saga",
			"version": "1.01",
			"author": "Gaardus"
		},
		{
			"id": "DIGIMONWORLDRE",
			"title": "Digimon World Re:Digitize",
			"version": "1.00",
			"author": "Gaardus"
		},
		{
			"id": "DISSIDIA012ALT",
			"title": "Dissidia Final Fantasy - Duodecim 012",
			"version": "1.01",
			"author": "Gaardus"
		},
		{
			"id": "DJMAXP3",
			"title": "DJMax Portable 3",
			"version": "1.00",
			"author": "Gaardus"
		},
		{
			"id": "ECHOCHROME",
			"title": "Echochrome",
			"version": "2.00",
			"manual": "true",
			"author": "Gaardus"
		},
		{
			"id": "FFIII2",
			"title": "Final Fantasy III",
			"version": "1.01",
			"author": "Gaardus"
		},
		{
			"id": "FFT0",
			"title": "Final Fantasy Type-0",
			"version": "1.01",
			"author": "Gaardus"
		},
		{
			"id": "GRANDKNIGHTSHISTORY",
			"title": "Grand Knights History",
			"version": "1.01",
			"author": "Gaardus"
		},
		{
			"id": "HALFMINUTEHERO",
			"title": "Half Minute Hero",
			"version": "1.01",
			"author": "Gaardus"
		},
		{
			"id": "HARVESTMOONHLV",
			"title": "Harvest Moon - Hero of Leaf Valley",
			"version": "1.01",
			"author": "Gaardus"
		},
		{
			"id": "INVIZIMALS",
			"title": "InviZimals",
			"version": "1.01",
			"author": "Gaardus"
		},
		{
			"id": "JEANNEDARC2",
			"title": "Jeanne d'Arc",
			"version": "1.01",
			"author": "Gaardus"
		},
		{
			"id": "KNIGHTNIGHT2",
			"title": "Knights in the Nightmare",
			"version": "1.01",
			"author": "Gaardus"
		},
		{
			"id": "KURULINFUSION",
			"title": "Kurulin Fusion",
			"version": "1.00",
			"author": "Gaardus"
		},
		{
			"id": "MFCDX",
			"title": "Mighty Flip Champs! DX",
			"version": "1.01",
			"author": "Gaardus"
		},
		{
			"id": "PACMANCE",
			"title": "Pac-Man Championship Edition",
			"version": "1.01",
			"author": "Gaardus"
		},
		{
			"id": "PANGYA",
			"title": "Pangya: Fantasy Golf",
			"version": "1.01",
			"author": "Gaardus"
		},
		{
			"id": "PATAPON",
			"title": "Patapon",
			"version": "2.00",
			"manual": "true",
			"author": "Gaardus"
		},
		{
			"id": "PATAPON3",
			"title": "Patapon 3",
			"version": "1.01",
			"author": "Gaardus"
		},
		{
			"id": "PERSONA",
			"title": "Persona",
			"version": "1.01",
			"author": "Gaardus"
		},
		{
			"id": "PERSONA2IS",
			"title": "Persona 2 Innocent Sin",
			"version": "1.01",
			"author": "Gaardus"
		},
		{
			"id": "PERSONA3P",
			"title": "Persona 3 Portable",
			"version": "1.01",
			"author": "Gaardus"
		},
		{
			"id": "RIVIERA",
			"title": "Riviera - The Promised Land",
			"version": "1.01",
			"author": "Gaardus"
		},
		{
			"id": "SEGAGENESISCOLLECTION",
			"title": "SEGA Genesis Collection",
			"version": "1.01",
			"author": "Gaardus"
		},
		{
			"id": "SPACEINVADERSEXTREME",
			"title": "Space Invaders Extreme",
			"version": "1.01",
			"author": "Gaardus"
		},
		{
			"id": "TITS",
			"title": "The Legend of Heroes: Trails in the Sky",
			"version": "2.00",
			"manual": "true",
			"author": "Gaardus"
		},
		{
			"id": "TITSSC1",
			"title": "The Legend of Heroes: Trails in the Sky SC - Disc 1",
			"version": "1.00",
			"author": "Gaardus"
		},
		{
			"id": "TITSSC2",
			"title": "The Legend of Heroes: Trails in the Sky SC - Disc 2",
			"version": "1.00",
			"author": "Gaardus"
		},
		{
			"id": "VALHALLAKNIGHTS",
			"title": "Valhalla Knights",
			"version": "1.00",
			"author": "Gaardus"
		},
		{
			"id": "YGGDRA2",
			"title": "Yggdra Union",
			"version": "2.00",
			"author": "Gaardus"
		},
		{
			"id": "YS1AND2CHRONICLES2",
			"title": "Ys 1 and 2 Chronicles",
			"version": "1.00",
			"manual": "true",
			"author": "Gaardus"
		},
		{
			"id": "YSOATH",
			"title": "Ys: The Oath in Felghana",
			"version": "1.00",
			"manual": "true",
			"author": "Gaardus"
		},
		{
			"id": "YSSEVEN2",
			"title": "Ys Seven",
			"version": "1.00",
			"manual": "true",
			"author": "Gaardus"
		},
		{
			"id": "ZHP",
			"title": "Z.H.P. Unlosing Ranger VS Darkdeath Evilman",
			"version": "2.00",
			"manual": "true",
			"author": "Gaardus"
		},
		{
			"id": "ASTONISHIASTORY",
			"title": "Astonisha Story",
			"version": "1.00",
			"author": "capSilver"
		},
		{
			"id": "BRANDISHDARKREVENANT",
			"title": "Brandish - The Dark Revenant",
			"version": "1.00",
			"author": "capSilver"
		},
		{
			"id": "BRAVESTORYNEWTRAVELER",
			"title": "Brave Story - New Traveler",
			"version": "1.00",
			"author": "capSilver"
		},
		{
			"id": "BURNOUTLEGENDS",
			"title": "Burnout - Legends",
			"version": "1.00",
			"author": "capSilver"
		},
		{
			"id": "CASTLEVANIADRCULAXCHRONICLES",
			"title": "Castlevania - The Dracula X Chronicles",
			"version": "1.00",
			"author": "capSilver"
		},
		{
			"id": "CHAOSHEADNORTH",
			"title": "Chaos - Head North",
			"version": "1.00",
			"author": "capSilver"
		},
		{
			"id": "CORPSEPARTY",
			"title": "Corpse Party",
			"version": "1.00",
			"author": "capSilver"
		},
		{
			"id": "CORPSEPARTYBOKOFSHADOWS",
			"title": "Corpse Party - Book of Shadows",
			"version": "1.00",
			"author": "capSilver"
		},
		{
			"id": "CRIMSONGEMSAGACS",
			"title": "Crimson Gem Saga",
			"version": "1.00",
			"author": "capSilver"
		},
		{
			"id": "FFVIICRISISCORE",
			"title": "Final Fantasy VII - Crisis Core",
			"version": "1.00",
			"author": "capSilver"
		},
		{
			"id": "DANTESINFERNO",
			"title": "Dantes Inferno",
			"version": "1.00",
			"author": "capSilver"
		},
		{
			"id": "DARKSTALKERSCHRONICLECHAOSTOWER",
			"title": "Darkstalkers Chronicle- The Chaos Tower",
			"version": "1.00",
			"author": "capSilver"
		},
		{
			"id": "DAXTER",
			"title": "Daxter",
			"version": "1.00",
			"author": "capSilver"
		},
		{
			"id": "DTRRECKONING",
			"title": "Dead to Rights - Reckoning",
			"version": "1.00",
			"author": "capSilver"
		},
		{
			"id": "DRAGONEERSARIAALT",
			"title": "Dragoneers Aria",
			"version": "1.00",
			"author": "capSilver"
		},
		{
			"id": "DUNGEONSIEGETHRONEAGONY",
			"title": "Dungeon Siege - The Throne of Agony",
			"version": "1.00",
			"author": "capSilver"
		},
		{
			"id": "FFTACTICSWAROFLIONSCS",
			"title": "Final Fantasy Tactics - The War of Lions",
			"version": "1.00",
			"author": "capSilver"
		},
		{
			"id": "FFTYPE0CS",
			"title": "Final Fantasy - Type 0",
			"version": "1.00",
			"author": "capSilver"
		},
		{
			"id": "FMABROTHERHOOD",
			"title": "Full Metal Alchemist - Brotherhood",
			"version": "1.00",
			"author": "capSilver"
		},
		{
			"id": "GITAROOMANLIVES",
			"title": "Gitarooman Lives",
			"version": "1.00",
			"author": "capSilver"
		},
		{
			"id": "GKHISTORY",
			"title": "Grand Knight History",
			"version": "1.00",
			"author": "capSilver"
		},
		{
			"id": "GOWCHAINSOLYMPUS",
			"title": "God of War - Chains of Olympus",
			"version": "1.00",
			"author": "capSilver"
		},
		{
			"id": "GOWGHOSTSPARTA",
			"title": "God of War - Ghost of Sparta",
			"version": "1.00",
			"author": "capSilver"
		},
		{
			"id": "GROWLANCERWOT",
			"title": "Growlanser - Wayfarer of Time",
			"version": "1.00",
			"author": "capSilver"
		},
		{
			"id": "GTACHINATOWNWARS",
			"title": "Grand Theft Auto - Chinatown Wars",
			"version": "1.00",
			"author": "capSilver"
		},
		{
			"id": "GTALIBERTYCITYSTORIES",
			"title": "Grand Theft Auto - Liberty City Stories",
			"version": "1.00",
			"author": "capSilver"
		},
		{
			"id": "GTAVICECITYSTORIES",
			"title": "Grand Theft Auto - Vice City Stories",
			"version": "1.00",
			"author": "capSilver"
		},
		{
			"id": "GUNSHOWDOWN",
			"title": "Gun - Showdown",
			"version": "1.00",
			"author": "capSilver"
		},
		{
			"id": "GURUMINMA",
			"title": "Gurumin - A Monstorous Adventure",
			"version": "1.00",
			"author": "capSilver"
		},
		{
			"id": "HALFMINUTEHERO2",
			"title": "Half Minute Hero 2 - The Second Coming",
			"version": "1.00",
			"author": "capSilver"
		},
		{
			"id": "HALFMINUTEHEROCS",
			"title": "Half Minute Hero",
			"version": "1.00",
			"author": "capSilver"
		},
		{
			"id": "HEXYSFORCE",
			"title": "Hexys Force",
			"version": "1.00",
			"author": "capSilver"
		},
		{
			"id": "JEANNEDARC",
			"title": "Jeanne D-Arc",
			"version": "1.00",
			"author": "capSilver"
		},
		{
			"id": "JUICED2",
			"title": "Juiced 2",
			"version": "1.00",
			"author": "capSilver"
		},
		{
			"id": "KHBBS",
			"title": "Kingdom Hearts - Birth By Sleep",
			"version": "1.00",
			"author": "capSilver"
		},
		{
			"id": "KILLZONELIBERATION",
			"title": "Killzone - Liberation",
			"version": "1.00",
			"author": "capSilver"
		},
		{
			"id": "KINGDOMOFPARADISE",
			"title": "Kingdom of Paradise",
			"version": "1.00",
			"author": "capSilver"
		},
		{
			"id": "LEGOSTARWARSORIGINALTRILOGY",
			"title": "Lego Star Wars - The Original Trilogy",
			"version": "1.00",
			"author": "capSilver"
		},
		{
			"id": "LITTLEBIGPLANET",
			"title": "Little Big Planet",
			"version": "1.00",
			"author": "capSilver"
		},
		{
			"id": "LOCOROCO1",
			"title": "Loco Roco",
			"version": "1.00",
			"author": "capSilver"
		},
		{
			"id": "LOCOROCO2CS",
			"title": "Loco Roco 2",
			"version": "1.00",
			"author": "capSilver"
		},
		{
			"id": "MANHUNT2",
			"title": "Manhunt 2",
			"version": "1.00",
			"author": "capSilver"
		},
		{
			"id": "MARVELULTIMATEALLIANCE",
			"title": "Marvel Ultimate Alliance",
			"version": "1.00",
			"author": "capSilver"
		},
		{
			"id": "MEDIEVILRESSURECTION",
			"title": "MediEvil - Resurrection",
			"version": "1.00",
			"author": "capSilver"
		},
		{
			"id": "MEMYKATAMARI",
			"title": "Me and My Katamari",
			"version": "1.00",
			"author": "capSilver"
		},
		{
			"id": "MC3DUBEDITION",
			"title": "Midnight Club 3 - Dub Edition",
			"version": "1.00",
			"author": "capSilver"
		},
		{
			"id": "MGPEACEWALKER",
			"title": "Metal Gear Solid - Peace Walker",
			"version": "1.00",
			"author": "capSilver"
		},
		{
			"id": "MHFREEDOMU",
			"title": "Monster Hunter - Freedom Unite",
			"version": "1.00",
			"author": "capSilver"
		},
		{
			"id": "MSARCTICEDGE",
			"title": "Motor Storm - Arctic Edge",
			"version": "1.00",
			"author": "capSilver"
		},
		{
			"id": "OBSCUREAFTERMATH",
			"title": "Obscure - Aftermath",
			"version": "1.00",
			"author": "capSilver"
		},
		{
			"id": "OUTRUN06C2C",
			"title": "Outrun 2006 - Coast to Coast",
			"version": "1.00",
			"author": "capSilver"
		},
		{
			"id": "PARAPPATHERAPPER",
			"title": "Parappa The Rapper",
			"version": "1.00",
			"author": "capSilver"
		},
		{
			"id": "PARODIUS",
			"title": "Parodius Portable",
			"version": "1.00",
			"author": "capSilver"
		},
		{
			"id": "PATAPONCS",
			"title": "Patapon",
			"version": "1.00",
			"author": "capSilver"
		},
		{
			"id": "PATAPON2CS",
			"title": "Patapon 2",
			"version": "1.00",
			"author": "capSilver"
		},
		{
			"id": "PATAPON3CS",
			"title": "Patapon 3",
			"version": "1.00",
			"author": "capSilver"
		},
		{
			"id": "POPOLOCROIS",
			"title": "PoPoLoCrois",
			"version": "1.00",
			"author": "capSilver"
		},
		{
			"id": "POWERSTONECOLLECTION",
			"title": "Power Stone Collection",
			"version": "1.00",
			"author": "capSilver"
		},
		{
			"id": "POPREVEL",
			"title": "Prince of Persia - Revelations",
			"version": "1.00",
			"author": "capSilver"
		},
		{
			"id": "RESISTANCERESTRIBUTION",
			"title": "Resistance Retribution",
			"version": "1.00",
			"author": "capSilver"
		},
		{
			"id": "RIVIERAPROMISEDLAND",
			"title": "Riviera - The Promised Land",
			"version": "1.00",
			"author": "capSilver"
		},
		{
			"id": "SMTPERSONA",
			"title": "Shin Megami Tensei - Persona",
			"version": "1.00",
			"author": "capSilver"
		},
		{
			"id": "SMTP2INNOCENT",
			"title": "Shin Megami Tensei - Persona 2 - Innocent Sin",
			"version": "1.00",
			"author": "capSilver"
		},
		{
			"id": "SMTP3P",
			"title": "Shin Megami Tensei - Persona 3 Portable",
			"version": "1.00",
			"author": "capSilver"
		},
		{
			"id": "SILENTHILLO",
			"title": "Silent Hill - Origins",
			"version": "1.00",
			"author": "capSilver"
		},
		{
			"id": "SILENTHILLSM",
			"title": "Silent Hill - Shattered Memories",
			"version": "1.00",
			"author": "capSilver"
		},
		{
			"id": "SCESSENTIALS",
			"title": "Splinter Cell - Essentials",
			"version": "1.00",
			"author": "capSilver"
		},
		{
			"id": "SPLITSECOND",
			"title": "Split Second",
			"version": "1.00",
			"author": "capSilver"
		},
		{
			"id": "SOFIRSTDEPARTURE",
			"title": "Star Ocean - First Departure",
			"version": "1.00",
			"author": "capSilver"
		},
		{
			"id": "SOSECONDEVO",
			"title": "Star Ocean - Second Evolution",
			"version": "1.00",
			"author": "capSilver"
		},
		{
			"id": "SWBATTLEFRONTELITES",
			"title": "Star Wars Battlefront - Elite Squadron",
			"version": "1.00",
			"author": "capSilver"
		},
		{
			"id": "SWBATTLEFRONTII",
			"title": "Star Wars - Battlefront II",
			"version": "1.00",
			"author": "capSilver"
		},
		{
			"id": "SUMMONNIGHT5",
			"title": "Summon Night 5",
			"version": "1.00",
			"author": "capSilver"
		},
		{
			"id": "SFDARKMIRROR",
			"title": "Syphon Filter - Dark Mirror",
			"version": "1.00",
			"author": "capSilver"
		},
		{
			"id": "SFLOGANSHADOW",
			"title": "Syphon Filer - Logans Shadow",
			"version": "1.00",
			"author": "capSilver"
		},
		{
			"id": "TOCLINGTOGETHER",
			"title": "Tactics Ogre - Let Us Cling Together",
			"version": "1.00",
			"author": "capSilver"
		},
		{
			"id": "TALESOFETERNIA",
			"title": "Tales of Eternia",
			"version": "1.00",
			"author": "capSilver"
		},
		{
			"id": "THETHIRDBIRTHDAY",
			"title": "The 3rd Birthday",
			"version": "1.00",
			"author": "capSilver"
		},
		{
			"id": "TLHTRAILSZERO",
			"title": "The Legend of Heroes - Trails from Zero",
			"version": "1.00",
			"author": "capSilver"
		},
		{
			"id": "TLHTRAILSSKYFC",
			"title": "The Legend of Heroes - Trails in the Sky FC",
			"version": "1.00",
			"author": "capSilver"
		},
		{
			"id": "TLHTRAILSSKYSCDISC1",
			"title": "The Legend of Heroes - Trails in the Sky SC Disc 1",
			"version": "1.00",
			"author": "capSilver"
		},
		{
			"id": "TLHTRAILSSKYSCDISC2",
			"title": "The Legend of Heroes - Trails in the Sky SC Disc 2",
			"version": "1.00",
			"author": "capSilver"
		},
		{
			"id": "TLHTRAILSAZURE",
			"title": "The Legend of Heroes - Trails of Azure",
			"version": "1.00",
			"author": "capSilver"
		},
		{
			"id": "THEWARRIORS",
			"title": "The Warriors",
			"version": "1.00",
			"author": "capSilver"
		},
		{
			"id": "TOCARACE2",
			"title": "TOCA - Race Driver 2",
			"version": "1.00",
			"author": "capSilver"
		},
		{
			"id": "TONYHAWKP8",
			"title": "Tony Hawk - Project 8",
			"version": "1.00",
			"author": "capSilver"
		},
		{
			"id": "TONYHAWKU2REMIX",
			"title": "Tony Hawk - Underground 2 Remix",
			"version": "1.00",
			"author": "capSilver"
		},
		{
			"id": "ULTIMATEGNG",
			"title": "Ultimate Ghostsn Goblins",
			"version": "1.00",
			"author": "capSilver"
		},
		{
			"id": "ULBROTHERHOODBLADE",
			"title": "Untold Legends - Brotherhood of the Blade",
			"version": "1.00",
			"author": "capSilver"
		},
		{
			"id": "VALKRRIAC2",
			"title": "Valkyria Chronicles 2",
			"version": "1.00",
			"author": "capSilver"
		},
		{
			"id": "VALKYRIAC3",
			"title": "Valkyria Chronicles 3",
			"version": "1.00",
			"author": "capSilver"
		},
		{
			"id": "XMENLEGENDS2ROA",
			"title": "X-Men Legends II - Rise of Apocalypse",
			"version": "1.00",
			"author": "capSilver"
		},
		{
			"id": "YSOF",
			"title": "Ys - Oath in Feighana",
			"version": "1.00",
			"author": "capSilver"
		},
		{
			"id": "YSSEVENCS",
			"title": "Ys - Seven",
			"version": "1.00",
			"author": "capSilver"
		},
		{
			"id": "YS1AND2CHRONICLES",
			"title": "Ys 1 and 2 - Chronicles",
			"version": "1.00",
			"author": "capSilver"
		},
		{
			"id": "ZHPUNLOSINGRANGER",
			"title": "ZHP - Unlosing Ranger VS Darkdeath Evilman",
			"version": "1.00",
			"author": "capSilver"
		},
		{
			"id": "POPREV",
			"title": "Prince of Persia: Revelations",
			"version": "1.00",
			"author": "MoonshineIndustries"
		},
		{
			"id": "POPRS",
			"title": "Prince of Persia: Rival Swords",
			"version": "1.00",
			"author": "MoonshineIndustries"
		},
		{
			"id": "POPTFS",
			"title": "Prince of Persia: The Forgotten Sands",
			"version": "1.00",
			"author": "MoonshineIndustries"
		},
		{
			"id": "CRASHBASHDU",
			"title": "Crash Bash",
			"version": "1.00",
			"author": "ElDuniels"
		},
		{
			"id": "ISSPROEVODU",
			"title": "ISS Pro Evolution",
			"version": "1.00",
			"author": "ElDuniels"
		},
		{
			"id": "MEDIEVILIIDU",
			"title": "Medievil II",
			"version": "1.00",
			"author": "ElDuniels"
		},
		{
			"id": "RATCHECLANKSIZEMATTERSDU",
			"title": "Ratchet Clank Size Matters",
			"version": "1.00",
			"author": "ElDuniels"
		},
		{
			"id": "SECRETAGENTCLANKDU",
			"title": "Secret Agent Clank",
			"version": "1.00",
			"author": "ElDuniels"
		},
		{
			"id": "SWFORCEDU",
			"title": "Stars Wars The Force Unleashed",
			"version": "1.00",
			"author": "ElDuniels"
		},
		{
			"id": "AC_BLOODLINES",
			"title": "Assassins Creed - Bloodlines",
			"version": "1.00",
			"author": "Swervito"
		},
		{
			"id": "GOW_COFOLYMPUS",
			"title": "God of War - Chains of Olympus",
			"version": "1.00",
			"author": "Swervito"
		},
		{
			"id": "GOW_GOFSPARTA",
			"title": "God of War - Ghost of Sparta",
			"version": "1.00",
			"author": "Swervito"
		},
		{
			"id": "GTA_LIBERTYCS",
			"title": "Grand Theft Auto - Liberty City Stories",
			"version": "1.00",
			"author": "Swervito"
		},
		{
			"id": "GTA_VICECS",
			"title": "Grand Theft Auto - Vice City Stories",
			"version": "1.00",
			"author": "Swervito"
		},
		{
			"id": "KH_BBSLEEP",
			"title": "Kingdom Hearts - Birth by Sleep",
			"version": "1.00",
			"author": "Swervito"
		},
		{
			"id": "MH2",
			"title": "Manhunt 2",
			"version": "1.00",
			"author": "Swervito"
		},
		{
			"id": "SDVSR06",
			"title": "SmackDown Vs Raw 2006",
			"version": "1.00",
			"author": "Swervito"
		},
		{
			"id": "SDVSR07",
			"title": "SmackDown Vs Raw 2007",
			"version": "1.00",
			"author": "Swervito"
		},
		{
			"id": "SDVSR09",
			"title": "SmackDown Vs Raw 2009",
			"version": "1.00",
			"author": "Swervito"
		},
		{
			"id": "SPIDERMAN2",
			"title": "Spiderman 2",
			"version": "1.00",
			"author": "Swervito"
		},
		{
			"id": "SW_BF2",
			"title": "Star Wars - BattleFront 2",
			"version": "1.00",
			"author": "Swervito"
		},
		{
			"id": "SW_BFSQUAD",
			"title": "Star Wars - Battlefront Renegade Squadron",
			"version": "1.00",
			"author": "Swervito"
		},
		{
			"id": "CRASHBAMDICOOT3IN1",
			"title": "Crash Bandicoot (3-in-1)",
			"version": "1.00",
			"author": "Rockstock7"
		},
		{
			"id": "GTURISMO1",
			"title": "Gran Turismo 1",
			"version": "1.00",
			"author": "GAD__Alexander"
		},
		{
			"id": "GTURISMO1JAP",
			"title": "Gran Turismo 1 Jap",
			"version": "1.00",
			"author": "GAD__Alexander"
		},
		{
			"id": "GTURISMO2JAP",
			"title": "Gran Turismo 2 Jap",
			"version": "1.00",
			"author": "GAD__Alexander"
		},
		{
			"id": "GTURISMO2",
			"title": "Gran Turismo 2",
			"version": "1.00",
			"author": "GAD__Alexander"
		},
		{
			"id": "GTURISMOPSP",
			"title": "Gran Turismo PSP",
			"version": "1.00",
			"author": "GAD__Alexander"
		},
		{
			"id": "IDOLMASTERPERFECTSUN",
			"title": "IDOLMASTER SP PERFECT SUN",
			"version": "1.00",
			"author": "setasorcer"
		},
		{
			"id": "INITIALDSTREETSTAGE",
			"title": "INITIALD STREET STAGE",
			"version": "1.00",
			"author": "setasorcer"
		},
		{
			"id": "KEIONHOUKAGOLIVE",
			"title": "K-ON! Houkago Live!!",
			"version": "1.00",
			"author": "setasorcer"
		},
		{
			"id": "PARODIUSPORTABLE",
			"title": "PARODIUS PORTABLE",
			"version": "1.00",
			"author": "setasorcer"
		},
		{
			"id": "SUZUMIYAHARUHINOYAKUSOKU",
			"title": "The Promise of Haruhi Suzumiya",
			"version": "1.00",
			"author": "setasorcer"
		},
		{
			"id": "TORADORAPORTABLE",
			"title": "TORADORAP!",
			"version": "1.00",
			"author": "setasorcer"
		}
	]
}
